reconcile_core/__init__.py
reconcile_core/reconcile_core.pyi
reconcile_core/tests/test_reconcilation_summary.py
reconcile_core-0.1.1.dist-info/WHEEL
reconcile_core-0.1.1.dist-info/METADATA
reconcile_core-0.1.1.dist-info/RECORD
