Metadata-Version: 2.1
Name: reconcile-core
Version: 0.1.1
Summary: Reconciliation library
Author: Simon Andrieux
Requires-Python: >=3.8,<4.0
Classifier: Programming Language :: Python :: 3
Classifier: Programming Language :: Python :: 3.8
Classifier: Programming Language :: Python :: 3.9
Classifier: Programming Language :: Python :: 3.10
Classifier: Programming Language :: Python :: 3.11
